abstractflow/__init__.py
abstractflow/__main__.py
abstractflow/cli.py
abstractflow/compiler.py
abstractflow/py.typed
abstractflow/runner.py
abstractflow/adapters/__init__.py
abstractflow/adapters/agent_adapter.py
abstractflow/adapters/control_adapter.py
abstractflow/adapters/effect_adapter.py
abstractflow/adapters/event_adapter.py
abstractflow/adapters/function_adapter.py
abstractflow/adapters/subflow_adapter.py
abstractflow/adapters/variable_adapter.py
abstractflow/core/__init__.py
abstractflow/core/flow.py
abstractflow/visual/__init__.py
abstractflow/visual/agent_ids.py
abstractflow/visual/builtins.py
abstractflow/visual/code_executor.py
abstractflow/visual/event_ids.py
abstractflow/visual/executor.py
abstractflow/visual/interfaces.py
abstractflow/visual/models.py
abstractflow/visual/session_runner.py
abstractflow/visual/workspace_scoped_tools.py
abstractflow-0.3.0.dist-info/licenses/LICENSE
abstractflow-0.3.0.dist-info/METADATA
abstractflow-0.3.0.dist-info/WHEEL
abstractflow-0.3.0.dist-info/entry_points.txt
abstractflow-0.3.0.dist-info/top_level.txt
abstractflow-0.3.0.dist-info/RECORD
