Metadata-Version: 2.4
Name: abstractflow
Version: 0.3.0
Summary: Diagram-based AI workflow generation built on AbstractCore
Author-email: AbstractFlow Team <contact@abstractflow.ai>
Maintainer-email: AbstractFlow Team <contact@abstractflow.ai>
License-Expression: MIT
Project-URL: Homepage, https://github.com/lpalbou/AbstractFlow
Project-URL: Documentation, https://abstractflow.readthedocs.io
Project-URL: Repository, https://github.com/lpalbou/AbstractFlow
Project-URL: Bug Tracker, https://github.com/lpalbou/AbstractFlow/issues
Project-URL: Changelog, https://github.com/lpalbou/AbstractFlow/blob/main/CHANGELOG.md
Keywords: ai,workflow,diagram,llm,automation,visual-programming,abstractcore,machine-learning
Classifier: Development Status :: 2 - Pre-Alpha
Classifier: Intended Audience :: Developers
Classifier: Intended Audience :: Science/Research
Classifier: Operating System :: OS Independent
Classifier: Programming Language :: Python :: 3
Classifier: Programming Language :: Python :: 3.10
Classifier: Programming Language :: Python :: 3.11
Classifier: Programming Language :: Python :: 3.12
Classifier: Topic :: Scientific/Engineering :: Artificial Intelligence
Classifier: Topic :: Software Development :: Libraries :: Python Modules
Classifier: Topic :: System :: Distributed Computing
Requires-Python: >=3.10
License-File: LICENSE
Requires-Dist: AbstractRuntime>=0.4.0
Requires-Dist: abstractcore[tools]>=2.6.8
Requires-Dist: pydantic>=2.0.0
Requires-Dist: typing-extensions>=4.0.0
Provides-Extra: agent
Requires-Dist: abstractagent>=0.2.0; extra == "agent"
Provides-Extra: dev
Requires-Dist: pytest>=7.0.0; extra == "dev"
Requires-Dist: pytest-asyncio>=0.21.0; extra == "dev"
Requires-Dist: black>=23.0.0; extra == "dev"
Requires-Dist: isort>=5.12.0; extra == "dev"
Requires-Dist: flake8>=6.0.0; extra == "dev"
Requires-Dist: mypy>=1.0.0; extra == "dev"
Requires-Dist: pre-commit>=3.0.0; extra == "dev"
Provides-Extra: server
Requires-Dist: fastapi>=0.100.0; extra == "server"
Requires-Dist: uvicorn[standard]>=0.23.0; extra == "server"
Requires-Dist: websockets>=11.0.0; extra == "server"
Provides-Extra: ui
Requires-Dist: streamlit>=1.28.0; extra == "ui"
Requires-Dist: plotly>=5.15.0; extra == "ui"
Requires-Dist: networkx>=3.1.0; extra == "ui"
Provides-Extra: all
Requires-Dist: abstractflow[agent,dev,server,ui]; extra == "all"
Dynamic: license-file
